steam_info_mcp/__init__.py
steam_info_mcp/__main__.py
steam_info_mcp/functions.py
steam_info_mcp-0.1.1.dist-info/METADATA
steam_info_mcp-0.1.1.dist-info/WHEEL
steam_info_mcp-0.1.1.dist-info/entry_points.txt
steam_info_mcp-0.1.1.dist-info/licenses/LICENSE
steam_info_mcp-0.1.1.dist-info/RECORD
