Metadata-Version: 2.4
Name: steam-info-mcp
Version: 0.1.1
Summary: Model Context Protocol Server Exposing Steam Web API Tools
Author: Beta
Maintainer: Beta
License: MIT License
License-File: LICENSE
Keywords: game-stats,mcp,model-context-protocol,steam,steam-web-api
Classifier: Development Status :: 4 - Beta
Classifier: Intended Audience :: Developers
Classifier: License :: OSI Approved :: MIT License
Classifier: Operating System :: OS Independent
Classifier: Programming Language :: Python :: 3
Classifier: Programming Language :: Python :: 3.9
Classifier: Programming Language :: Python :: 3.10
Classifier: Programming Language :: Python :: 3.11
Classifier: Programming Language :: Python :: 3.12
Classifier: Topic :: Games/Entertainment
Classifier: Topic :: Internet :: WWW/HTTP :: Dynamic Content
Classifier: Topic :: Software Development :: Libraries :: Python Modules
Requires-Python: >=3.9
Requires-Dist: mcp>=0.1.0
Requires-Dist: requests>=2.31.0
